store_vpetrov/__init__.py
store_vpetrov/config.py
store_vpetrov/database.py
store_vpetrov-0.1.1.dist-info/LICENSE
store_vpetrov-0.1.1.dist-info/METADATA
store_vpetrov-0.1.1.dist-info/WHEEL
store_vpetrov-0.1.1.dist-info/top_level.txt
store_vpetrov-0.1.1.dist-info/RECORD
