Metadata-Version: 2.1
Name: store_vpetrov
Version: 0.1.1
License-File: LICENSE
Requires-Dist: fastapi
Requires-Dist: pydantic
Requires-Dist: sqlalchemy
